virtualenvutils/__init__.py
virtualenvutils/__main__.py
virtualenvutils/virtualenvutils.py
virtualenvutils-0.6.3.dist-info/LICENSE
virtualenvutils-0.6.3.dist-info/METADATA
virtualenvutils-0.6.3.dist-info/WHEEL
virtualenvutils-0.6.3.dist-info/entry_points.txt
virtualenvutils-0.6.3.dist-info/namespace_packages.txt
virtualenvutils-0.6.3.dist-info/top_level.txt
virtualenvutils-0.6.3.dist-info/RECORD
