Metadata-Version: 2.1
Name: virtualenvutils
Version: 0.6.3
Summary: manage virtualenv/-m venv based utilities
Home-page: https://sourceforge.net/p/virtualenvutils/code/ci/default/tree
Author: Anthon van der Neut
Author-email: a.van.der.neut@ruamel.eu
License: MIT License
Keywords: virtualenv utilities
Classifier: Development Status :: 4 - Beta
Classifier: Intended Audience :: Developers
Classifier: License :: OSI Approved :: MIT License
Classifier: Operating System :: OS Independent
Classifier: Programming Language :: Python
Requires-Python: >=3
License-File: LICENSE
Requires-Dist: ruamel.std.pathlib
